mpgg/__init__.py
mpgg/mpgg.py
mpgg/utilities.py
mpgg-1.0.0.dist-info/LICENSE
mpgg-1.0.0.dist-info/WHEEL
mpgg-1.0.0.dist-info/METADATA
mpgg-1.0.0.dist-info/RECORD
