Metadata-Version: 2.1
Name: mpgg
Version: 1.0.0
Summary: Streamlined MPEG-1 and MPEG-2 source loader and helper utility for VapourSynth
Home-page: https://github.com/rlaphoenix/mpgg
License: GPL-3.0-only
Keywords: vapoursynth,dvd,mpeg,mpeg2
Author: rlaphoenix
Author-email: rlaphoenix@pm.me
Requires-Python: >=3.8,<4.0
Classifier: Development Status :: 4 - Beta
Classifier: Environment :: Other Environment
Classifier: Intended Audience :: End Users/Desktop
Classifier: License :: OSI Approved :: GNU General Public License v3 (GPLv3)
Classifier: Natural Language :: English
Classifier: Operating System :: OS Independent
Classifier: Programming Language :: Python :: 3
Classifier: Programming Language :: Python :: 3.8
Classifier: Programming Language :: Python :: 3.9
Classifier: Programming Language :: Python :: 3.10
Classifier: Programming Language :: Python :: 3.11
Classifier: Topic :: Multimedia :: Video
Requires-Dist: more-itertools (>=9.1.0,<10.0.0)
Requires-Dist: pyd2v (>=1.3.0,<2.0.0)
Requires-Dist: pymediainfo (>=6.0.1,<7.0.0)
Requires-Dist: pymp4 (>=1.2.0,<2.0.0)
Requires-Dist: vapoursynth (>=50)
Project-URL: Repository, https://github.com/rlaphoenix/mpgg
